cmx/__init__.py
cmx/data.py
cmx/utils.py
cmx/with_hack.py
cmx/backends/__init__.py
cmx/backends/components.py
cmx/backends/html.py
cmx/backends/latex.py
cmx/backends/markdown.py
cmx/server/__init__.py
cmx-0.0.46.dist-info/licenses/LICENSE
tassa/__init__.py
tassa/events.py
tassa/schemas.py
tassa/server.py
cmx-0.0.46.dist-info/METADATA
cmx-0.0.46.dist-info/WHEEL
cmx-0.0.46.dist-info/top_level.txt
cmx-0.0.46.dist-info/RECORD
