Metadata-Version: 2.4
Name: cmx
Version: 0.0.46
Home-page: https://github.com/cmx/cmx-python
Author: Ge Yang<ge.ike.yang@gmail.com>
Author-email: ge.ike.yang@gmail.com
License: MIT
Classifier: Development Status :: 3 - Alpha
Classifier: Programming Language :: Python
Requires-Python: >=3.8.6
License-File: LICENSE
Requires-Dist: functional_notations
Provides-Extra: dev
Requires-Dist: black==22.3.0; extra == "dev"
Requires-Dist: pylint==2.13.4; extra == "dev"
Requires-Dist: pytest==7.1.2; extra == "dev"
Dynamic: author
Dynamic: author-email
Dynamic: home-page
Dynamic: license-file
